<?xml version="1.0" encoding="UTF-8"?>
<modification>
<id><![CDATA[Customer See All Notify Order History]]></id>
<version><![CDATA[OC v.1.5.6.5 Merkent]]></version>
<vqmver><![CDATA[2.6.1]]></vqmver>
<author><![CDATA[frymi - IP_CAM]]></author>
<email><![CDATA[webmaster@opencart.li]]></email>
<link><![CDATA[http://www.opencart.li]]></link>

<file name="catalog/model/account/order.php">
<operation error="log">
<search position="replace"><![CDATA[$query = $this->db->query("SELECT date_added, os.name AS status, oh.comment, oh.notify FROM " . DB_PREFIX . "order_history oh LEFT JOIN " . DB_PREFIX . "order_status os ON oh.order_status_id = os.order_status_id WHERE oh.order_id = '" . (int)$order_id . "' AND oh.notify = '1' AND os.language_id = '" . (int)$this->config->get('config_language_id') . "' ORDER BY oh.date_added");]]></search>
<add><![CDATA[
	$query = $this->db->query("SELECT date_added, os.name AS status, oh.comment, oh.notify FROM " . DB_PREFIX . "order_history oh LEFT JOIN " . DB_PREFIX . "order_status os ON oh.order_status_id = os.order_status_id WHERE oh.order_id = '" . (int)$order_id . "' AND os.language_id = '" . (int)$this->config->get('config_language_id') . "' ORDER BY oh.date_added");
]]></add>
</operation>
</file>
 
</modification>